btensor/__init__.py
btensor/array.py
btensor/basis.py
btensor/basistuple.py
btensor/exceptions.py
btensor/space.py
btensor/tensor.py
btensor/tensorsum.py
btensor/decomp/__init__.py
btensor/decomp/hosvd.py
btensor/numpy_functions/__init__.py
btensor/numpy_functions/core.py
btensor/numpy_functions/einsum.py
btensor/numpy_functions/linalg/__init__.py
btensor/numpy_functions/linalg/eigh.py
btensor/util/__init__.py
btensor/util/matrix.py
btensor/util/util.py
BTensor-1.1.2.dist-info/LICENSE
BTensor-1.1.2.dist-info/METADATA
BTensor-1.1.2.dist-info/NOTICE
BTensor-1.1.2.dist-info/WHEEL
BTensor-1.1.2.dist-info/top_level.txt
BTensor-1.1.2.dist-info/RECORD
