Metadata-Version: 2.1
Name: BTensor
Version: 1.1.2
Summary: A library for basis transformation of tensors
Author-email: Max Nusspickel <max.nusspickel@gmail.com>
Project-URL: source, https://github.com/maxnus/btensor
Classifier: Programming Language :: Python :: 3
Classifier: Programming Language :: Python :: 3.8
Classifier: Programming Language :: Python :: 3.9
Classifier: Programming Language :: Python :: 3.10
Classifier: Programming Language :: Python :: 3.11
Classifier: License :: OSI Approved :: Apache Software License
Classifier: Operating System :: OS Independent
Requires-Python: >=3.8
License-File: LICENSE
License-File: NOTICE
Requires-Dist: numpy >=1.19.0
Requires-Dist: scipy >=1.1.0
